{
  "configVersion": 1,
  "timestamp": 1740324532177,
  "index": "/travel-packlist/index.html",
  "assetGroups": [
    {
      "name": "app",
      "installMode": "prefetch",
      "updateMode": "prefetch",
      "cacheQueryOptions": {
        "ignoreVary": true
      },
      "urls": [
        "/travel-packlist/chunk-0853c747.js",
        "/travel-packlist/chunk-1fe62964.js",
        "/travel-packlist/chunk-2e26ae71.js",
        "/travel-packlist/chunk-34431619.js",
        "/travel-packlist/chunk-3b243499.js",
        "/travel-packlist/chunk-4327e78b.js",
        "/travel-packlist/chunk-47168cb5.js",
        "/travel-packlist/chunk-5c30dbee.js",
        "/travel-packlist/chunk-607b59f8.js",
        "/travel-packlist/chunk-6118c1a5.js",
        "/travel-packlist/chunk-63bc588b.js",
        "/travel-packlist/chunk-73ab9c80.js",
        "/travel-packlist/chunk-74ff73aa.js",
        "/travel-packlist/chunk-7df9a7b3.js",
        "/travel-packlist/chunk-8a9a02b3.js",
        "/travel-packlist/chunk-8d22869a.js",
        "/travel-packlist/chunk-9572a377.js",
        "/travel-packlist/chunk-a19fb5de.js",
        "/travel-packlist/chunk-a22c312e.js",
        "/travel-packlist/chunk-ad6d2de6.js",
        "/travel-packlist/chunk-afa126bf.js",
        "/travel-packlist/chunk-bc5e67aa.js",
        "/travel-packlist/chunk-cd1e44c0.js",
        "/travel-packlist/chunk-da5c6bf3.js",
        "/travel-packlist/chunk-e0b7ddf0.js",
        "/travel-packlist/chunk-e0f6ac3a.js",
        "/travel-packlist/chunk-eb86e6a0.js",
        "/travel-packlist/chunk-f23b6b73.js",
        "/travel-packlist/chunk-f2e03ef8.js",
        "/travel-packlist/chunk-fd242edf.js",
        "/travel-packlist/icon-128.webp",
        "/travel-packlist/icon-192.webp",
        "/travel-packlist/icon-256.webp",
        "/travel-packlist/icon-48.webp",
        "/travel-packlist/icon-512.webp",
        "/travel-packlist/icon-72.webp",
        "/travel-packlist/icon-96.webp",
        "/travel-packlist/icon.svg",
        "/travel-packlist/index.de.html",
        "/travel-packlist/index.html",
        "/travel-packlist/main-3954165d.js",
        "/travel-packlist/main-7424b1d8.js",
        "/travel-packlist/manifest.json",
        "/travel-packlist/polyfills-55a01abb.js",
        "/travel-packlist/polyfills-9e0c948b.js",
        "/travel-packlist/styles-933e52c7.css"
      ],
      "patterns": []
    }
  ],
  "dataGroups": [],
  "hashTable": {
    "/travel-packlist/chunk-0853c747.js": "0853c7476201595f2caa41839762ac52fa12947e",
    "/travel-packlist/chunk-1fe62964.js": "1fe62964cbdfcb2b62ce85cdfca93a3721c88725",
    "/travel-packlist/chunk-2e26ae71.js": "2e26ae718da96ef3f6c8a9279f2a4849d78a4070",
    "/travel-packlist/chunk-34431619.js": "34431619d9e5ef77a8977c509ad86809d58aa0e1",
    "/travel-packlist/chunk-3b243499.js": "3b24349970b815a219e4f8b84dbc39b3682c4a76",
    "/travel-packlist/chunk-4327e78b.js": "4327e78bc3e27fa5a7b72f9a9ce8c207d34c0c5a",
    "/travel-packlist/chunk-47168cb5.js": "47168cb5d4efca697b19540cca97abe827ee0241",
    "/travel-packlist/chunk-5c30dbee.js": "5c30dbeed0bfb849d82948959b21586c8e563976",
    "/travel-packlist/chunk-607b59f8.js": "607b59f8ed1591ca9b8e0ef949817787f30c2bb9",
    "/travel-packlist/chunk-6118c1a5.js": "6118c1a5a487a8fbd02b632f906961ed4bfbf835",
    "/travel-packlist/chunk-63bc588b.js": "63bc588b9a8b22690be7587aa3c79ed88ba76732",
    "/travel-packlist/chunk-73ab9c80.js": "73ab9c80537d87c4d6e95e89a1ddf22ce2e95df3",
    "/travel-packlist/chunk-74ff73aa.js": "74ff73aa58c6c08eb287337c46677c1955dfb7ec",
    "/travel-packlist/chunk-7df9a7b3.js": "7df9a7b3da68a2e76fa2ab4c215916b2cde818ee",
    "/travel-packlist/chunk-8a9a02b3.js": "8a9a02b33fa88e96a1deed3d730593516c5f9f8a",
    "/travel-packlist/chunk-8d22869a.js": "8d22869a1720e2b6ebbd5d35d3bcd12a5d0f3ee5",
    "/travel-packlist/chunk-9572a377.js": "9572a377a40803a6adb30d92363c9d944c69cf25",
    "/travel-packlist/chunk-a19fb5de.js": "a19fb5de5a1b33f759e05062c63f455502dd4fad",
    "/travel-packlist/chunk-a22c312e.js": "a22c312e1847835ab1d4ac231be631254d73fa94",
    "/travel-packlist/chunk-ad6d2de6.js": "ad6d2de6dbef0feb7278fa0986c25b2d6a7f8828",
    "/travel-packlist/chunk-afa126bf.js": "afa126bf542a17e664a679d26ba4d72a13b3b7a7",
    "/travel-packlist/chunk-bc5e67aa.js": "bc5e67aa2390e40bdc299c145158c549d62d1c9a",
    "/travel-packlist/chunk-cd1e44c0.js": "cd1e44c0c50c6a246a33aacb509910d8b07904b9",
    "/travel-packlist/chunk-da5c6bf3.js": "da5c6bf3d4b90d96c4ac0dc17a42c3b737a1c2c1",
    "/travel-packlist/chunk-e0b7ddf0.js": "e0b7ddf07a07f247916f8580b53c7061feeb48a0",
    "/travel-packlist/chunk-e0f6ac3a.js": "e0f6ac3ac78c6f0683fd15f59fb4bac3d545ec82",
    "/travel-packlist/chunk-eb86e6a0.js": "eb86e6a0e1f039b85907d1c663a28a5345195f4e",
    "/travel-packlist/chunk-f23b6b73.js": "f23b6b733e72eedaf2f64c2499f4a84206645119",
    "/travel-packlist/chunk-f2e03ef8.js": "f2e03ef8059f54995ca1f2e43863af1c2c97b306",
    "/travel-packlist/chunk-fd242edf.js": "fd242edf53cc1b214fa70089f7414c1a7b665e20",
    "/travel-packlist/icon-128.webp": "7e61d315a1cd696c5f330c835dffe36a649c62a9",
    "/travel-packlist/icon-192.webp": "43d52c7e19968420a0c8a2746d0cc5d71c380b4e",
    "/travel-packlist/icon-256.webp": "5db331cd4b7c6af2ff733a8054ffca6d840df9c8",
    "/travel-packlist/icon-48.webp": "96eadf92f4ebb06e82b754c8e98116430906da45",
    "/travel-packlist/icon-512.webp": "f359dcd5dfbba6324a4f3f920b8313a2d8a5124a",
    "/travel-packlist/icon-72.webp": "562f312b9640379edb50a0b7baca254c15c82f61",
    "/travel-packlist/icon-96.webp": "dfcb6479dfe2c75a058c31162564dc54d48a967e",
    "/travel-packlist/icon.svg": "59a86293cf9a39dbe04e37ab08bc8bb6012812a6",
    "/travel-packlist/index.de.html": "7419c1c54b0c70b5190abad9c03849cf61f8b2dd",
    "/travel-packlist/index.html": "1bd8ac001259176588c76282a722b3114850f892",
    "/travel-packlist/main-3954165d.js": "3954165de984053c6a636b1d78175311f15586fc",
    "/travel-packlist/main-7424b1d8.js": "7424b1d86e0daa3b79c721ca8983d82b29052981",
    "/travel-packlist/manifest.json": "11378120154335d21752ed67f989324c4696701b",
    "/travel-packlist/polyfills-55a01abb.js": "55a01abb463b3cb832ef23700764a405e54ae6ea",
    "/travel-packlist/polyfills-9e0c948b.js": "9e0c948b534d2e93edc8fac9c73ba80ccfa7f55a",
    "/travel-packlist/styles-933e52c7.css": "933e52c7957e4835017781940e3a18d8c93bc3d0"
  },
  "navigationUrls": [
    {
      "positive": true,
      "regex": "^\\/.*$"
    },
    {
      "positive": false,
      "regex": "^\\/(?:.+\\/)?[^/]*\\.[^/]*$"
    },
    {
      "positive": false,
      "regex": "^\\/(?:.+\\/)?[^/]*__[^/]*$"
    },
    {
      "positive": false,
      "regex": "^\\/(?:.+\\/)?[^/]*__[^/]*\\/.*$"
    }
  ],
  "navigationRequestStrategy": "performance"
}