{
  "configVersion": 1,
  "timestamp": 1780867980430,
  "index": "/travel-packlist/index.html",
  "assetGroups": [
    {
      "name": "app",
      "installMode": "prefetch",
      "updateMode": "prefetch",
      "cacheQueryOptions": {
        "ignoreVary": true
      },
      "urls": [
        "/travel-packlist/build-info.json",
        "/travel-packlist/chunk-012e0815.js",
        "/travel-packlist/chunk-05920a15.js",
        "/travel-packlist/chunk-097734b3.js",
        "/travel-packlist/chunk-0af8f499.js",
        "/travel-packlist/chunk-20b61ec6.js",
        "/travel-packlist/chunk-294620d6.js",
        "/travel-packlist/chunk-3553e598.js",
        "/travel-packlist/chunk-398cde82.js",
        "/travel-packlist/chunk-442e58e1.js",
        "/travel-packlist/chunk-453c9524.js",
        "/travel-packlist/chunk-4d68f611.js",
        "/travel-packlist/chunk-5259c398.js",
        "/travel-packlist/chunk-6130059a.js",
        "/travel-packlist/chunk-695e5934.js",
        "/travel-packlist/chunk-8679bc95.js",
        "/travel-packlist/chunk-94b774aa.js",
        "/travel-packlist/chunk-9a987ae9.js",
        "/travel-packlist/chunk-a4abf758.js",
        "/travel-packlist/chunk-b4ddfb7f.js",
        "/travel-packlist/chunk-c70fc8ef.js",
        "/travel-packlist/chunk-cefe6dce.js",
        "/travel-packlist/chunk-dffac486.js",
        "/travel-packlist/chunk-e1452629.js",
        "/travel-packlist/chunk-eae062b5.js",
        "/travel-packlist/chunk-eb0fabfd.js",
        "/travel-packlist/chunk-f2819e92.js",
        "/travel-packlist/chunk-f4a435e0.js",
        "/travel-packlist/chunk-f59eab3e.js",
        "/travel-packlist/chunk-f5a38f78.js",
        "/travel-packlist/chunk-f858ba55.js",
        "/travel-packlist/icon-128.webp",
        "/travel-packlist/icon-192.webp",
        "/travel-packlist/icon-256.webp",
        "/travel-packlist/icon-48.webp",
        "/travel-packlist/icon-512.webp",
        "/travel-packlist/icon-72.webp",
        "/travel-packlist/icon-96.webp",
        "/travel-packlist/icon.svg",
        "/travel-packlist/index.de.html",
        "/travel-packlist/index.html",
        "/travel-packlist/main-63211b1e.js",
        "/travel-packlist/main-a28739ea.js",
        "/travel-packlist/manifest.json",
        "/travel-packlist/polyfills-502e60a8.js",
        "/travel-packlist/polyfills-c36609ec.js",
        "/travel-packlist/styles-7540d292.css"
      ],
      "patterns": []
    }
  ],
  "dataGroups": [],
  "hashTable": {
    "/travel-packlist/build-info.json": "162f88950eb76f206935c36cb0f2651882b0235e",
    "/travel-packlist/chunk-012e0815.js": "012e08150e6c23a920285c3f12783858bc8baf18",
    "/travel-packlist/chunk-05920a15.js": "05920a15c43a6d289a3b81dfb33fd2fde79dc2e7",
    "/travel-packlist/chunk-097734b3.js": "097734b3cfb89c67871e5100792637a696f760e5",
    "/travel-packlist/chunk-0af8f499.js": "0af8f499362ad7e567a71c464ee7a98c353764f5",
    "/travel-packlist/chunk-20b61ec6.js": "20b61ec62f2d936279e350532722a5cf50d9961b",
    "/travel-packlist/chunk-294620d6.js": "294620d6f0c0945c5fa8ffe2c62c2a1a13c83b75",
    "/travel-packlist/chunk-3553e598.js": "3553e598c31b9971696b049a6979f325db313c1c",
    "/travel-packlist/chunk-398cde82.js": "398cde82d1f96c1c1e377fc4322d293d5f00edf5",
    "/travel-packlist/chunk-442e58e1.js": "442e58e17c2d92ca2c409024014611c4d2164971",
    "/travel-packlist/chunk-453c9524.js": "453c95246d2e2d2e383a76581c0d763b2f534b17",
    "/travel-packlist/chunk-4d68f611.js": "4d68f6112143e7ca475f5cf60880aebce42926b8",
    "/travel-packlist/chunk-5259c398.js": "5259c398259ba37d365662606f737f90a6556692",
    "/travel-packlist/chunk-6130059a.js": "6130059a56337cb592554a8a0c92abb8d55b5659",
    "/travel-packlist/chunk-695e5934.js": "695e59340c09e14304e05ec06101e33755490224",
    "/travel-packlist/chunk-8679bc95.js": "8679bc95e536621d7d912c62ab72ccf484ec9100",
    "/travel-packlist/chunk-94b774aa.js": "94b774aab44b685700c6240a00081193cb4184a4",
    "/travel-packlist/chunk-9a987ae9.js": "9a987ae92a035d16c19357e4532592ae05a9c44f",
    "/travel-packlist/chunk-a4abf758.js": "a4abf7582cda9c41ba4382b27d34e681bf7862d2",
    "/travel-packlist/chunk-b4ddfb7f.js": "b4ddfb7ffcf05ea8dcf9dfe3028681e024a4d648",
    "/travel-packlist/chunk-c70fc8ef.js": "c70fc8ef1955c82ff7ecb81448617c64bcabfc91",
    "/travel-packlist/chunk-cefe6dce.js": "cefe6dcebd82e57b7ebb1feec7e60cd880b5b886",
    "/travel-packlist/chunk-dffac486.js": "dffac4864ea14202e99adcf1c293ec81730202f4",
    "/travel-packlist/chunk-e1452629.js": "e145262935ac40aee42928e0201300733eb6b3ab",
    "/travel-packlist/chunk-eae062b5.js": "eae062b554f28960f6eb41dc2c4a695b4634e0c0",
    "/travel-packlist/chunk-eb0fabfd.js": "eb0fabfd86c2f3368628ead13c13503c27b1fc8c",
    "/travel-packlist/chunk-f2819e92.js": "f2819e9245ec2e7cae83fb16164b6be34a18ce0c",
    "/travel-packlist/chunk-f4a435e0.js": "f4a435e016017536cfc2c16fb6c5faaa28803ef0",
    "/travel-packlist/chunk-f59eab3e.js": "f59eab3e0f68544f5ecf777a7049b78d4bc52ea4",
    "/travel-packlist/chunk-f5a38f78.js": "f5a38f7801d4afa13aed204db270c7fd29d9fb7f",
    "/travel-packlist/chunk-f858ba55.js": "f858ba5541b5ae2b7a5612d00244b8ad5fb8ea29",
    "/travel-packlist/icon-128.webp": "7e61d315a1cd696c5f330c835dffe36a649c62a9",
    "/travel-packlist/icon-192.webp": "43d52c7e19968420a0c8a2746d0cc5d71c380b4e",
    "/travel-packlist/icon-256.webp": "5db331cd4b7c6af2ff733a8054ffca6d840df9c8",
    "/travel-packlist/icon-48.webp": "96eadf92f4ebb06e82b754c8e98116430906da45",
    "/travel-packlist/icon-512.webp": "f359dcd5dfbba6324a4f3f920b8313a2d8a5124a",
    "/travel-packlist/icon-72.webp": "562f312b9640379edb50a0b7baca254c15c82f61",
    "/travel-packlist/icon-96.webp": "dfcb6479dfe2c75a058c31162564dc54d48a967e",
    "/travel-packlist/icon.svg": "59a86293cf9a39dbe04e37ab08bc8bb6012812a6",
    "/travel-packlist/index.de.html": "c9aae436e36f0a4f728144edb3e756330aca8aa8",
    "/travel-packlist/index.html": "27aecc0e6fae71a7d0cd275f54588969e46b406a",
    "/travel-packlist/main-63211b1e.js": "63211b1e7c32eca5b5aacbc5af40cc7166dad8ff",
    "/travel-packlist/main-a28739ea.js": "a28739ea950f15b0e7581e404f8b996cc7dd169b",
    "/travel-packlist/manifest.json": "11378120154335d21752ed67f989324c4696701b",
    "/travel-packlist/polyfills-502e60a8.js": "502e60a8d33c7e1fbd8fc961b48f79ee7fcaeddb",
    "/travel-packlist/polyfills-c36609ec.js": "c36609ec2ae2b15a2bf8a9051325d7462f2c9576",
    "/travel-packlist/styles-7540d292.css": "7540d29298145659d4b3eca6104b9334108720f5"
  },
  "navigationUrls": [
    {
      "positive": true,
      "regex": "^\\/.*$"
    },
    {
      "positive": false,
      "regex": "^\\/(?:.+\\/)?[^/]*\\.[^/]*$"
    },
    {
      "positive": false,
      "regex": "^\\/(?:.+\\/)?[^/]*__[^/]*$"
    },
    {
      "positive": false,
      "regex": "^\\/(?:.+\\/)?[^/]*__[^/]*\\/.*$"
    }
  ],
  "navigationRequestStrategy": "performance"
}